LICENSE.txt
MANIFEST.in
README.markdown
setup.py
disqus/__init__.py
disqus/api.py
disqus/models.py
disqus/tests.py
disqus/wxr_feed.py
disqus/management/__init__.py
disqus/management/commands/__init__.py
disqus/management/commands/disqus_dumpdata.py
disqus/management/commands/disqus_export.py
disqus/templates/disqus/num_replies.html
disqus/templates/disqus/recent_comments.html
disqus/templates/disqus/show_comments.html
disqus/templatetags/__init__.py
disqus/templatetags/disqus_tags.py
django17_disqus.egg-info/PKG-INFO
django17_disqus.egg-info/SOURCES.txt
django17_disqus.egg-info/dependency_links.txt
django17_disqus.egg-info/not-zip-safe
django17_disqus.egg-info/top_level.txt