Metadata-Version: 1.1
Name: django17-disqus
Version: 0.4.3
Summary: Export comments and integrate DISQUS into your Django website. Fix for Django 1.7. Thanks Arthur...
Home-page: https://github.com/jalemolina/django-disqus
Author: Alejandro Molina
Author-email: jalemolina@gmail.com
License: New BSD License
Platform: UNKNOWN
Classifier: Framework :: Django
Classifier: Intended Audience :: Developers
Classifier: License :: OSI Approved :: BSD License
Classifier: Programming Language :: Python
